ngram_graphs/Generator.py
ngram_graphs/__init__.py
ngram_graphs/comparison.py
ngram_graphs/utils.py
ngram_graphs/TextGraph/IGraphTextGraph.py
ngram_graphs/TextGraph/NetworkxTextGraph.py
ngram_graphs/TextGraph/__init__.py
ngram_graphs/tests/__init__.py
ngram_graphs/tests/test_graphs.py
ngram_graphs-0.1.14.dist-info/LICENSE.txt
ngram_graphs-0.1.14.dist-info/METADATA
ngram_graphs-0.1.14.dist-info/WHEEL
ngram_graphs-0.1.14.dist-info/top_level.txt
ngram_graphs-0.1.14.dist-info/RECORD
