Metadata-Version: 2.1
Name: ngram-graphs
Version: 0.1.14
Summary: An igraph or networkx based ngram graph library for NLP
Home-page: https://github.com/loginn/ngrams_graphs
Author: loginn
Author-email: vincent.kurta2@gmail.com
License: MIT
Keywords: ngrams graph NLP
Platform: UNKNOWN
Classifier: Programming Language :: Python :: 3.6
Classifier: Topic :: Text Processing :: Linguistic
Requires-Dist: networkx
Requires-Dist: python-igraph
